gitflow_studio-1.0.4.dist-info/licenses/LICENSE
studio/__init__.py
studio/__main__.py
studio/cli.py
studio/core/__init__.py
studio/core/aliases.py
studio/core/app_context.py
studio/core/plugin_base.py
studio/core/plugin_loader.py
studio/core/themes.py
studio/db/__init__.py
studio/db/sqlite_manager.py
studio/git/__init__.py
studio/git/async_git.py
studio/git/git_operations.py
studio/github/__init__.py
studio/github/auth.py
studio/github/config_template.py
studio/github/repos.py
studio/plugins/__init__.py
studio/plugins/example_plugin.py
studio/tests/test_basic.py
studio/tests/test_comprehensive.py
studio/utils/__init__.py
studio/utils/advanced_search.py
studio/utils/backup_restore.py
studio/utils/batch_operations.py
studio/utils/code_quality_analyzer.py
studio/utils/export_manager.py
studio/utils/git_hooks_manager.py
studio/utils/performance_monitor.py
studio/utils/repo_discovery.py
studio/utils/security_scanner.py
studio/utils/sync_manager.py
studio/utils/workflow_automation.py
gitflow_studio-1.0.4.dist-info/METADATA
gitflow_studio-1.0.4.dist-info/WHEEL
gitflow_studio-1.0.4.dist-info/entry_points.txt
gitflow_studio-1.0.4.dist-info/top_level.txt
gitflow_studio-1.0.4.dist-info/RECORD
