Metadata-Version: 2.4
Name: gitflow-studio
Version: 1.0.4
Summary: A comprehensive Git workflow management CLI tool
Home-page: https://github.com/Sherin-SEF-AI/GitFlow-Studio
Author: Sherin Joseph Roy
Author-email: Sherin Joseph Roy <sherin.joseph2217@gmail.com>
Maintainer-email: Sherin Joseph Roy <sherin.joseph2217@gmail.com>
License: MIT
Project-URL: Homepage, https://github.com/Sherin-SEF-AI/GitFlow-Studio
Project-URL: Repository, https://github.com/Sherin-SEF-AI/GitFlow-Studio.git
Project-URL: Issues, https://github.com/Sherin-SEF-AI/GitFlow-Studio/issues
Keywords: git,workflow,cli,github,gitflow
Classifier: Development Status :: 4 - Beta
Classifier: Intended Audience :: Developers
Classifier: Operating System :: OS Independent
Classifier: Programming Language :: Python :: 3
Classifier: Programming Language :: Python :: 3.9
Classifier: Programming Language :: Python :: 3.10
Classifier: Programming Language :: Python :: 3.11
Classifier: Programming Language :: Python :: 3.12
Classifier: Topic :: Software Development :: Version Control :: Git
Requires-Python: >=3.9
License-File: LICENSE
Requires-Dist: GitPython>=3.1.0
Requires-Dist: aiosqlite>=0.17.0
Requires-Dist: aiohttp>=3.8.0
Requires-Dist: click>=8.0.0
Requires-Dist: rich>=12.0.0
Requires-Dist: PyGithub>=1.59.0
Requires-Dist: cryptography>=41.0.0
Requires-Dist: keyring>=24.0.0
Requires-Dist: psutil>=5.9.0
Dynamic: author
Dynamic: home-page
Dynamic: license-file
Dynamic: requires-python
